isONclust-0.0.5.data/scripts/isONclust
modules/__init__.py
modules/cluster.py
modules/cluster_parallel.py
modules/compute_shared_minimizers_probabilities.py
modules/get_sorted_fastq_for_cluster.py
modules/help_functions.py
modules/p_minimizers_shared.py
modules/parallelize.py
isONclust-0.0.5.dist-info/LICENSE.txt
isONclust-0.0.5.dist-info/METADATA
isONclust-0.0.5.dist-info/WHEEL
isONclust-0.0.5.dist-info/top_level.txt
isONclust-0.0.5.dist-info/RECORD
