Metadata-Version: 2.1
Name: isONclust
Version: 0.0.5
Summary: De novo clustering of long-read transcriptome reads.
Home-page: https://github.com/ksahlin/isONclust
Author: Kristoffer Sahlin
Author-email: kxs624@psu.edu
License: UNKNOWN
Keywords: Iso-Seq CCS PacBio Oxford Nanopore Technologies transcript long-read
Platform: UNKNOWN
Classifier: Development Status :: 3 - Alpha
Classifier: Programming Language :: Python :: 3
Classifier: Programming Language :: Python :: 3.4
Classifier: Programming Language :: Python :: 3.5
Classifier: Programming Language :: Python :: 3.6
Classifier: Programming Language :: Python :: 3.7
Requires-Python: !=3.0.*, !=3.1.*, !=3.2.*, !=3.3.*, <4
Requires-Dist: pysam (>=0.11)
Requires-Dist: parasail (>=1.1.11)
